{
  "shots": [
    {
      "x": "37.13",
      "y": "48.33",
      "number": "5",
      "timestamp": 1777812227462
    },
    {
      "x": "9.70",
      "y": "67.36",
      "number": "7",
      "timestamp": 1777812293761
    },
    {
      "x": "65.11",
      "y": "51.97",
      "number": "2",
      "timestamp": 1777812363001
    },
    {
      "x": "88.81",
      "y": "87.23",
      "number": "8",
      "timestamp": 1777812500832
    },
    {
      "x": "23.69",
      "y": "84.71",
      "number": "20",
      "timestamp": 1777812565614
    },
    {
      "x": "77.05",
      "y": "81.91",
      "number": "20",
      "timestamp": 1777812658310
    },
    {
      "x": "14.37",
      "y": "49.73",
      "number": "2",
      "timestamp": 1777812808988
    },
    {
      "x": "90.67",
      "y": "71.84",
      "number": "20",
      "timestamp": 1777813036822
    },
    {
      "x": "27.99",
      "y": "76.60",
      "number": "15",
      "timestamp": 1777813080412
    },
    {
      "x": "78.73",
      "y": "69.60",
      "number": "15",
      "timestamp": 1777813106022
    },
    {
      "x": "82.09",
      "y": "79.12",
      "number": "9",
      "timestamp": 1777813158225
    },
    {
      "x": "87.87",
      "y": "14.19",
      "number": "20",
      "timestamp": 1777813173105
    },
    {
      "x": "28.92",
      "y": "58.69",
      "number": "14",
      "timestamp": 1777813262869
    },
    {
      "x": "80.04",
      "y": "41.06",
      "number": "20",
      "timestamp": 1777813298022
    },
    {
      "x": "9.33",
      "y": "35.74",
      "number": "14",
      "timestamp": 1777813525037
    }
  ],
  "gameNote": "Timeout: 14:53",
  "filters": {
    "showOnly": null,
    "hiddenNumbers": []
  }
}